Workbook

Sheet Overview
A1: GALP | B1: 2024
A3: Module | B3: Transaction type | C3: Transactions/year | D3: Process cost savings per transaction(/year) | E3: Sum | F3: FTE savings
A4: SRM (incl performance management) | B4: Onboarded/enabled suppliers | C4: 1974 | D4: =SRM!B5 -> 240 | E4: =D4*C4 -> 473760 | F4: =E4/SRM!B1 -> 7.896
A5: Sourcing | B5: Sourcing events | C5: =6022*0.2 -> 1204.4 | D5: =Sourcing!B5 -> 480 | E5: =D5*C5 -> 578112 | F5: =E5/Sourcing!B1 -> 9.6352
A6: Sourcing | B6: Quick-bids | C6: =6022*0.8 -> 4817.6 | D6: =D5*0.1 -> 48 | E6: =D6*C6 -> 231244.8 | F6: =E6/Sourcing!B1 -> 3.85408
A7: Contract | B7: Contracts | C7: 6776 | D7: =Contracts!B5 -> 48 | E7: =D7*C7 -> 325248 | F7: =E7/Contracts!B1 -> 5.4208
A8: eCatalog | B8: Shopping carts | D8: =eCatalog!B5 -> 5.3571429 | E8: =D8*C8 -> 0 | F8: =E8/eCatalog!B1 -> 0
A9: Invoicing | B9: Invoice | D9: =Invoice!B5 -> 2.3809524 | E9: =D9*C9 -> 0 | F9: =E9/Invoice!B1 -> 0
A10: PO | B10: Purchase order | D10: =PO!B5 -> 10.714286 | E10: =D10*C10 -> 0 | F10: =E10/PO!B1 -> 0
A11: ASN | B11: ASN items | D11: =ASN!B5 -> 1.5873016 | E11: =D11*C11 -> 0 | F11: =E11/ASN!B1 -> 0
A12: Forecast / Call Offs | B12: DELFOR | D12: =Forecast!B5 -> 3.4920635 | E12: =D12*C12 -> 0 | F12: =E12/Forecast!B1 -> 0
A13: VMI | B13: Materials via VMI | D13: =VMI!B5 -> 100 | E13: =D13*C13 -> 0 | F13: =E13/VMI!B1 -> 0
A14: Quality | B14: Complaints | D14: =Quality!B5 -> 14.285714 | E14: =D14*C14 -> 0 | F14: =E14/Quality!B1 -> 0
E17: =SUM(E4:E16) -> 1608364.8
D19: ARR | E19: 400000 | F19: =E17/E19 -> 4.020912 | G19: =F19 -> 4.020912 | H19: ROI

Sheet SRM
A1: Average cost per FTE per year | B1: 60000 | D1: Utilisation | E1: 0.8
A2: Suppliers managed per FTE | B2: 20
A3: Costs per supplier per year | B3: =B1*E1/B2 -> 2400
A4: Savings percentage per supplier | B4: 0.1
A5: Process costs savings per supplier | B5: =B4*B3 -> 240
A9: According to Bard/Gemini: how many suppliers should be managed per strategic procurment person | B9: General benchmarks: While individual capacity varies, studies suggest strategic procurement professionals can effectively manage: 5-10 complex, strategic suppliers: This requires significant time and effort dedicated to each supplier. 10-20 moderately complex suppliers: With efficient processes and technology, this range offers good balance between control and workload. 20+ standard suppliers: Automation and support become crucial to maintain effectiveness at larger scales
A11: According to Bard/Gemini: average saving per supplier by using a digital supplier management solution | B11: Reported savings ranges: While a precise average is elusive, reports and studies point to savings potential within these ranges: 5-20% reduction in direct procurement costs: This aligns with McKinsey & Company's report on digital procurement transformation. 10-30% savings on spend analysis and contract negotiation: Procurement automation and data insights can drive significant reductions. Double-digit improvement in inventory optimization and supplier performance: Streamlined processes and better visibility lead to cost savings.

Sheet Sourcing
A1: Average cost per FTE per year | B1: 60000 | D1: Utilisation | E1: 0.8
A2: Events managed per FTE per year | B2: 20
A3: Costs per event | B3: =B1*E1/B2 -> 2400
A4: Savings percentage per event | B4: 0.2
A5: Process cost savings per contract | B5: =B4*B3 -> 480
A9: According to Bard/Gemini: time savings per sourcing event using a fully integrated digital solution | B9: Reported time savings ranges: Studies and reports suggest potential time savings per sourcing event in the following ranges: 20-50% reduction in overall sourcing cycle time: This aligns with research by Procurement Leaders and PayStream Advisors. 30-40% faster supplier identification and qualification: Automated search, filtering, and pre-qualification features accelerate this stage. 25-35% time saved on proposal evaluation and scoring: Standardized templates, scoring tools, and data analysis streamline this process. 15-20% quicker contract negotiation and finalization: Automated workflows and centralized document management expedite these steps.
A11: According to Bard/Gemini: how many sourcing events are managed by a procurement person on average | B11: General benchmarks: While individual capacity varies, reports suggest procurement professionals might manage: 10-20 sourcing events per year: This applies to complex events requiring significant time and effort. 20-40 events per year: This range is possible with efficient processes and moderate-complexity events. 40+ events per year: Highly automated environments and supporting teams enable this higher volume, but might compromise individual attention.

Sheet Contracts
A1: Average cost per FTE per year | B1: 60000 | D1: Utilisation | E1: 0.8
A2: Contracts managed per FTE per year | B2: 200
A3: Costs per contract | B3: =B1*E1/B2 -> 240
A4: Savings percentage per contract | B4: 0.2
A5: Process cost savings per contract | B5: =B4*B3 -> 48
A9: According to Bard/Gemini: how many contracts are managed by a procurement person on average | B9: General benchmarks, but caution is advised: While individual capacity varies, reports suggest procurement professionals might manage: 50-200 active contracts: This applies to scenarios with moderate complexity and efficient processes. 200-500+ contracts: Highly automated platforms and dedicated support teams enable this higher volume, but individual focus might be compromised.
A11: According to Bard/Gemini: time savings per contract a fully integrated digital solution | B11: Reported time savings ranges: Studies and reports suggest potential time savings per contract in the following ranges: 20-40% reduction in overall contract lifecycle time: This aligns with research by IDC and Procurement Leaders. 30-50% faster contract drafting and negotiation: Automated templates, clause libraries, and collaboration tools expedite these steps. 25-35% time saved on approvals and finalization: Electronic workflows and centralized document management streamline approvals. 15-20% quicker risk assessments and compliance checks: Automated risk analysis tools and pre-built compliance checklists save time.

Sheet eCatalog
A1: Average cost per FTE per year | B1: 60000 | D1: Utilisation | E1: 0.8
A2: Minutes per requisition without epro | B2: 45
A3: Costs per preq | B3: =B1*E1/12/4.2/5/8/60*B2 -> 17.857143
A4: Savings percentage per req | B4: 0.3
A5: Process cost savings per req | B5: =B4*B3 -> 5.3571429
A9: According to Bard/Gemini: effort in minutes per requisition without an eprocurment solution | B9: Estimating effort without eprocurment: While precise figures are difficult, consider: Industry benchmarks: Average requisition processing time without eprocurment ranges from 30-60 minutes, depending on complexity. Internal data: If available, analyze past requisition processing times for a more specific estimate. Task breakdown: Estimate time for each task involved, such as item research, supplier selection, price comparison, approvals, and order placement. Potential effort reduction with eprocurment: Studies suggest eprocurment solutions can reduce requisition processing time by 20-40%. Applying this range to your estimated effort without eprocurment provides a potential time savings range.

Sheet Invoice
A1: Average cost per FTE per year | B1: 60000 | D1: Utilisation | E1: 0.8
A2: Minutes per invoice without P2P | B2: 15
A3: Costs per preq | B3: =B1*E1/12/4.2/5/8/60*B2 -> 5.952381
A4: Savings percentage per invoice | B4: 0.4
A5: Process cost savings per invoice | B5: =B4*B3 -> 2.3809524
A9: According to Bard/Gemini: effort in minutes per invoice without an P2P solution | B9: Estimating effort without a P2P solution: While precise figures are difficult, consider: Industry benchmarks: Average invoice processing time without a P2P solution can range from 10-20 minutes, depending on complexity. Internal data: If available, analyze past invoice processing times for a more specific estimate. Task breakdown: Estimate time for each task involved, such as data entry, matching, approvals, error correction, and payment processing. Potential effort reduction with a P2P solution: Studies suggest P2P solutions can reduce invoice processing time by 30-50%. Applying this range to your estimated effort without a P2P solution provides a potential time savings range. Additionally, consider: Automated data entry: Eliminates manual data entry errors and saves time. Automated matching: Quickly and accurately matches invoices to POs, reducing manual effort. Streamlined approvals: Electronic workflows speed up the approval process. Enhanced error detection: Automated rules flag potential errors for faster correction. Electronic payments: Saves time and eliminates manual tasks associated with traditional payment methods.

Sheet PO
A1: Average cost per FTE per year | B1: 60000 | D1: Utilisation | E1: 0.8
A2: Minutes per PO without ePro | B2: 90
A3: Costs per PO | B3: =B1*E1/12/4.2/5/8/60*B2 -> 35.714286
A4: Savings percentage per PO | B4: 0.3
A5: Process cost savings per PO | B5: =B4*B3 -> 10.714286
A9: According to Bard/Gemini: effort in minutes per PO without an eProcurment solution | B9: Estimating effort without eProcurement: Similar to requisitions, precise figures are difficult, but consider: Industry benchmarks: Average PO processing time without eProcurement can range from 60-120 minutes, depending on complexity. Internal data: If available, analyze past PO processing times for a more specific estimate. Task breakdown: Estimate time for each task involved, such as generating the PO, obtaining approvals, communicating with suppliers, and managing amendments. Potential effort reduction with eProcurement: Studies suggest eProcurement solutions can reduce PO processing time by 20-40%. Applying this range to your estimated effort without eProcurement provides a potential time savings range.

Sheet ASN
A1: Average cost per FTE per year | B1: 60000 | D1: Utilisation | E1: 0.8
A2: Minutes per ASN without a system | B2: 10
A3: Costs per ASN | B3: =B1*E1/12/4.2/5/8/60*B2 -> 3.968254
A4: Savings percentage per ASN | B4: 0.4
A5: Process cost savings per ASN | B5: =B4*B3 -> 1.5873016
A9: According to Bard/Gemini: effort in minutes per ASN without an eProcurment solution | B9: Estimating effort without eProcurement: While precise figures are difficult, consider: Industry benchmarks: Average ASN processing time without eProcurement can range from 5-15 minutes per item, depending on complexity. Internal data: If available, analyze past ASN processing times for a more specific estimate. Task breakdown: Estimate time for each task involved, such as data entry, verification, error correction, communication, and filing. Potential effort reduction with eProcurement: Studies suggest eProcurement solutions can reduce ASN processing time by 30-50%. Applying this range to your estimated effort without eProcurement provides a potential time savings range.

Sheet Forecast
A1: Average cost per FTE per year | B1: 60000 | D1: Utilisation | E1: 0.8
A2: Minutes per DELFOR without ePro | B2: 22
A3: Costs per DELFOR | B3: =B1*E1/12/4.2/5/8/60*B2 -> 8.7301587
A4: Savings percentage per DELFOR | B4: 0.4
A5: Process cost savings per DELFOR | B5: =B4*B3 -> 3.4920635
A9: According to Bard/Gemini: effort in minutes per DELFOR without an eProcurment solution | B9: Estimating effort without eProcurement: While precise figures are difficult, consider these approaches: Industry benchmarks: Average DELFOR processing time without eProcurement can range from 15-30 minutes per DELFOR, depending on complexity. Internal data: Analyze past DELFOR processing times for a more specific estimate if available. Task breakdown: Estimate time for each task involved, such as data entry, supplier verification, approval routing, and communication. Potential effort reduction with eProcurement: Studies suggest eProcurement solutions can reduce DELFOR processing time by 30-50%. Applying this range to your estimated effort without eProcurement provides a potential time savings range.

Sheet VMI
A1: Average cost per FTE per year | B1: 60000 | D1: Utilisation | E1: 0.8
A2: Minutes effort for disposition without VMI | B2: =60*12 -> 720 | C2: estimation: 60 min per month
A3: Costs per VMI material | B3: =B1*E1/12/4.2/5/8/60*B2 -> 285.71429
A4: Savings percentage per VMI material | B4: 0.35
A5: Process cost savings per VMI material | B5: =B4*B3 -> 100
A8: According to Bard/Gemini:

Sheet Quality
A1: Average cost per FTE per year | B1: 60000 | D1: Utilisation | E1: 0.8
A2: Minutes per complaint without system | B2: 120 | C2: estimate
A3: Costs per complaint | B3: =B1*E1/12/4.2/5/8/60*B2 -> 47.619048
A4: Savings percentage per complaint | B4: 0.3
A5: Process cost savings per complaint | B5: =B4*B3 -> 14.285714
A8: According to Bard/Gemini:
A9: effort for managing a reclamation in minutes | B9: Potential effort reduction with dedicated solutions: Studies suggest dedicated reclamation management software or integrated solutions within robust ERP systems can reduce processing time by 20-40%. Applying this range to your estimated effort without such solutions provides a potential savings range.
